setup.py
albion_api_client/__init__.py
albion_api_client/client.py
albion_api_client.egg-info/PKG-INFO
albion_api_client.egg-info/SOURCES.txt
albion_api_client.egg-info/dependency_links.txt
albion_api_client.egg-info/requires.txt
albion_api_client.egg-info/top_level.txt