Metadata-Version: 1.1
Name: albion-api-client
Version: 0.1.2
Summary: An API client for Albion Online written in Python.
Home-page: https://github.com/proelke/albion-api-client
Author: Patrick Roelke
Author-email: proelke@gmail.com
License: MIT
Keywords: api,ablion,online
Platform: UNKNOWN
Classifier: Development Status :: 3 - Alpha
Classifier: Intended Audience :: Developers
Classifier: License :: OSI Approved :: MIT License
Classifier: Programming Language :: Python :: 2
Classifier: Programming Language :: Python :: 2.7
Classifier: Programming Language :: Python :: 3
Classifier: Programming Language :: Python :: 3.3
Classifier: Programming Language :: Python :: 3.4
Classifier: Programming Language :: Python :: 3.5
